README.md
setup.py
GooblerPKG.egg-info/PKG-INFO
GooblerPKG.egg-info/SOURCES.txt
GooblerPKG.egg-info/dependency_links.txt
GooblerPKG.egg-info/requires.txt
GooblerPKG.egg-info/top_level.txt
gooblerpkg/__init__.py
gooblerpkg/start.py